mdsh5/__init__.py
mdsh5/read_mds.py
mdsh5/search_shots.py
mdsh5/config_examples/d3d.yml
mdsh5/config_examples/kstar.yml
mdsh5/config_examples/search_d3d.yml
mdsh5/config_examples/search_kstar.yml
mdsh5-0.1.3.dist-info/METADATA
mdsh5-0.1.3.dist-info/WHEEL
mdsh5-0.1.3.dist-info/entry_points.txt
mdsh5-0.1.3.dist-info/licenses/LICENSE
mdsh5-0.1.3.dist-info/RECORD
