Metadata-Version: 2.4
Name: mdsh5
Version: 0.1.3
Summary: A higher level python package that uses mdsthin to read MDSPlus data and store it in hdf5 formate for easy caching, viewing, distribution, and analysis.
Project-URL: Homepage, https://github.com/anchal-physics/mdsh5
Project-URL: Bug Reports, https://github.com/anchal-physics/mdsh5/issues
Project-URL: Source, https://github.com/anchal-physics/mdsh5
Author-email: Anchal Gupta <anchal.physics@gmail.com>
License:                                  Apache License
License-File: LICENSE
Keywords: HDF5,MDSPLus
Classifier: Development Status :: 3 - Alpha
Classifier: Intended Audience :: Developers
Classifier: Programming Language :: Python :: 3
Classifier: Topic :: Software Development :: Build Tools
Requires-Python: >=3.7
Requires-Dist: h5py>=3
Requires-Dist: mdsthin
Requires-Dist: pyyaml
Requires-Dist: tqdm
